bridgic/core/__init__.py
bridgic/core/agentic/__init__.py
bridgic/core/agentic/_concurrent_automa.py
bridgic/core/agentic/_sequential_automa.py
bridgic/core/agentic/react/__init__.py
bridgic/core/agentic/react/_react_automa.py
bridgic/core/agentic/react/templates/tools_chat.jinja
bridgic/core/agentic/tool_specs/__init__.py
bridgic/core/agentic/tool_specs/_automa_tool_spec.py
bridgic/core/agentic/tool_specs/_base_tool_spec.py
bridgic/core/agentic/tool_specs/_function_tool_spec.py
bridgic/core/agentic/types/__init__.py
bridgic/core/agentic/types/_chat_message.py
bridgic/core/agentic/workers/__init__.py
bridgic/core/agentic/workers/_tool_selection_worker.py
bridgic/core/automa/__init__.py
bridgic/core/automa/_automa.py
bridgic/core/automa/_graph_automa.py
bridgic/core/automa/_graph_meta.py
bridgic/core/automa/args/__init__.py
bridgic/core/automa/args/_args_binding.py
bridgic/core/automa/args/_args_descriptor.py
bridgic/core/automa/interaction/__init__.py
bridgic/core/automa/interaction/_event_handling.py
bridgic/core/automa/interaction/_human_interaction.py
bridgic/core/automa/worker/__init__.py
bridgic/core/automa/worker/_callable_worker.py
bridgic/core/automa/worker/_worker.py
bridgic/core/automa/worker/_worker_callback.py
bridgic/core/automa/worker/_worker_decorator.py
bridgic/core/config/__init__.py
bridgic/core/config/_global_setting.py
bridgic/core/model/__init__.py
bridgic/core/model/_base_llm.py
bridgic/core/model/protocols/__init__.py
bridgic/core/model/protocols/_structured_output.py
bridgic/core/model/protocols/_tool_selection.py
bridgic/core/model/types/__init__.py
bridgic/core/model/types/_content_block.py
bridgic/core/model/types/_message.py
bridgic/core/model/types/_response.py
bridgic/core/model/types/_tool_use.py
bridgic/core/prompt/__init__.py
bridgic/core/prompt/_base_template.py
bridgic/core/prompt/_ejinja_template.py
bridgic/core/prompt/_fstring_template.py
bridgic/core/prompt/utils/__init__.py
bridgic/core/prompt/utils/_prompt_utils.py
bridgic_core-0.2.1.dist-info/METADATA
bridgic_core-0.2.1.dist-info/WHEEL
bridgic_core-0.2.1.dist-info/licenses/LICENSE
bridgic_core-0.2.1.dist-info/RECORD
