Metadata-Version: 2.4
Name: bridgic-core
Version: 0.2.1
Summary: Core classes and abstractions of Bridgic, as well as basic implementations for the orchestration framework.
Author-email: Tielei Zhang <zhangtl04@gmail.com>
License: MIT
License-File: LICENSE
Classifier: Programming Language :: Python :: 3
Classifier: Programming Language :: Python :: 3.9
Classifier: Programming Language :: Python :: 3.10
Classifier: Programming Language :: Python :: 3.11
Classifier: Programming Language :: Python :: 3.12
Classifier: Programming Language :: Python :: 3.13
Requires-Python: >=3.9
Requires-Dist: cloudpickle>=3.1.2
Requires-Dist: docstring-parser>=0.16.0
Requires-Dist: jinja2>=3.1.0
Requires-Dist: msgpack>=1.1.1
Requires-Dist: pydantic<2.12.0,>=2.11.0
